drtsepackage/RecordData.py
drtsepackage/RecordTimeDrift.py
drtsepackage/RestartSpeedgoat.py
drtsepackage/SendReceiveFunctions.py
drtsepackage/__init__.py
drtsepackage-0.0.2.dist-info/LICENSE
drtsepackage-0.0.2.dist-info/METADATA
drtsepackage-0.0.2.dist-info/WHEEL
drtsepackage-0.0.2.dist-info/top_level.txt
drtsepackage-0.0.2.dist-info/RECORD
